nameko_pymemcache.py
nameko_pymemcache-0.1.3.dist-info/licenses/LICENSE
nameko_pymemcache-0.1.3.dist-info/METADATA
nameko_pymemcache-0.1.3.dist-info/WHEEL
nameko_pymemcache-0.1.3.dist-info/top_level.txt
nameko_pymemcache-0.1.3.dist-info/RECORD
