Metadata-Version: 2.4
Name: nameko-pymemcache
Version: 0.1.3
Summary: Memcached dependency for nameko services with consistent hashing
Home-page: https://github.com/andreasmyleus/nameko-pymemcache/
Author: andreasmyleus
Author-email: andreas@pdc.ax
License: Apache License, Version 2.0
Keywords: nameko memcached cache distributed consistent-hashing
Classifier: Development Status :: 4 - Beta
Classifier: License :: OSI Approved :: Apache Software License
Classifier: Intended Audience :: Developers
Classifier: Topic :: System :: Distributed Computing
Classifier: Programming Language :: Python :: 3
Classifier: Programming Language :: Python :: 3.8
Classifier: Programming Language :: Python :: 3.9
Classifier: Programming Language :: Python :: 3.10
Classifier: Programming Language :: Python :: 3.11
Classifier: Programming Language :: Python :: 3.12
Requires-Python: >=3.8
License-File: LICENSE
Requires-Dist: nameko>=2.0.0
Requires-Dist: pymemcache>=4.0.0
Dynamic: author
Dynamic: author-email
Dynamic: classifier
Dynamic: description
Dynamic: description-content-type
Dynamic: home-page
Dynamic: keywords
Dynamic: license
Dynamic: license-file
Dynamic: requires-dist
Dynamic: requires-python
Dynamic: summary
